facebook_fetcher/__init__.py
facebook_fetcher/__version__.py
facebook_fetcher/chats.py
facebook_fetcher/comments.py
facebook_fetcher/createaccount.py
facebook_fetcher/event.py
facebook_fetcher/exceptions.py
facebook_fetcher/group.py
facebook_fetcher/login.py
facebook_fetcher/messenger.py
facebook_fetcher/posts.py
facebook_fetcher/settings.py
facebook_fetcher/teste.py
facebook_fetcher/user.py
facebook_fetcher/utils.py
facebook_fetcher-1.0.2.dist-info/LICENSE
facebook_fetcher-1.0.2.dist-info/METADATA
facebook_fetcher-1.0.2.dist-info/WHEEL
facebook_fetcher-1.0.2.dist-info/top_level.txt
facebook_fetcher-1.0.2.dist-info/RECORD
