Metadata-Version: 2.1
Name: facebook_fetcher
Version: 1.0.2
Summary: Facebook scraper / Fetcher Unlimited by Andry RL
Home-page: https://github.com/Andryerics/facebook_fetcher
Author: Andry RL
Author-email: andryerics@gmail.com
License: MIT
Keywords: facebook-scraper,facebook-parser,facebook-scraper-without-apikey
Classifier: Development Status :: 3 - Alpha
Classifier: Intended Audience :: Developers
Classifier: Topic :: Software Development :: Build Tools
Classifier: License :: OSI Approved :: MIT License
Classifier: Natural Language :: English
Classifier: Programming Language :: Python :: 3
Classifier: Programming Language :: Python :: 3.7
Classifier: Programming Language :: Python :: 3.8
Classifier: Programming Language :: Python :: 3.9
Classifier: Programming Language :: Python :: 3.10
Classifier: Programming Language :: Python :: 3.11
Classifier: Programming Language :: Python :: 3 :: Only
Requires-Python: >=3.7
License-File: LICENSE
Requires-Dist: requests-toolbelt
Requires-Dist: requests
Requires-Dist: bs4
